subprocess_logger/__init__.py
subprocess_logger/subprocess_logger.py
subprocess_logger-0.3.0.dist-info/licenses/LICENSE
subprocess_logger-0.3.0.dist-info/METADATA
subprocess_logger-0.3.0.dist-info/WHEEL
subprocess_logger-0.3.0.dist-info/top_level.txt
subprocess_logger-0.3.0.dist-info/RECORD
