Metadata-Version: 2.4
Name: subprocess-logger
Version: 0.3.0
Summary: Consolidated handler for subprocess logging
Home-page: https://github.com/Vi-Nk/subprocess-logger/
Author: Vi-Nk
License: MIT License
Keywords: subprocess,logging,loggers
Classifier: Programming Language :: Python :: 3
Classifier: License :: OSI Approved :: MIT License
Classifier: Operating System :: OS Independent
Classifier: Development Status :: 4 - Beta
Classifier: Intended Audience :: Developers
Classifier: Topic :: Software Development :: Libraries :: Python Modules
Requires-Python: >=3.7
License-File: LICENSE
Dynamic: home-page
Dynamic: license-file
Dynamic: requires-python
